microsockets/__init__.py
microsockets/application.py
microsockets/events.py
microsockets/hooks.py
microsockets/rooms.py
microsockets/scopes.py
microsockets/socket.py
microsockets-1.0.0.dist-info/METADATA
microsockets-1.0.0.dist-info/WHEEL
microsockets-1.0.0.dist-info/top_level.txt
microsockets-1.0.0.dist-info/RECORD
