Metadata-Version: 2.1
Name: microsockets
Version: 1.0.0
Summary: ASGI Websocket server made with simplicity in mind.
Home-page: https://github.com/ParkerD559/microsockets-py
Author: David Parker
License: UNKNOWN
Platform: UNKNOWN
Classifier: Programming Language :: Python :: 3
Classifier: License :: OSI Approved :: MIT License
Classifier: Operating System :: OS Independent
